gl_connectors_cli/__init__.py
gl_connectors_cli/__main__.py
gl_connectors_cli/config.py
gl_connectors_cli/constants.py
gl_connectors_cli/main.py
gl_connectors_cli/utils.py
gl_connectors_cli/api/__init__.py
gl_connectors_cli/api/auth.py
gl_connectors_cli/api/base.py
gl_connectors_cli/api/integrations.py
gl_connectors_cli/api/models.py
gl_connectors_cli/api/users.py
gl_connectors_cli/commands/__init__.py
gl_connectors_cli/commands/auth.py
gl_connectors_cli/commands/base.py
gl_connectors_cli/commands/integrations.py
gl_connectors_cli/commands/users.py
gl_connectors_cli-0.1.0b1.dist-info/METADATA
gl_connectors_cli-0.1.0b1.dist-info/WHEEL
gl_connectors_cli-0.1.0b1.dist-info/entry_points.txt
gl_connectors_cli-0.1.0b1.dist-info/top_level.txt
gl_connectors_cli-0.1.0b1.dist-info/RECORD
